deployfolder/__init__.py
deployfolder/__main__.py
deployfolder/cli.py
deployfolder/main.py
deployfolder-0.3.0.dist-info/licenses/LICENSE
deployfolder-0.3.0.dist-info/METADATA
deployfolder-0.3.0.dist-info/WHEEL
deployfolder-0.3.0.dist-info/entry_points.txt
deployfolder-0.3.0.dist-info/top_level.txt
deployfolder-0.3.0.dist-info/RECORD
