Metadata-Version: 2.4
Name: deployfolder
Version: 0.3.0
Summary: A tool to create deployment folders based on YAML configuration
Author-email: Janosch Meyer <janosch.code@proton.me>
License: MIT License
Keywords: deployment,configuration,yaml,json,placeholders
Classifier: Development Status :: 4 - Beta
Classifier: Intended Audience :: Developers
Classifier: Intended Audience :: System Administrators
Classifier: License :: OSI Approved :: MIT License
Classifier: Programming Language :: Python :: 3
Classifier: Programming Language :: Python :: 3.7
Classifier: Programming Language :: Python :: 3.8
Classifier: Programming Language :: Python :: 3.9
Classifier: Programming Language :: Python :: 3.10
Classifier: Programming Language :: Python :: 3.11
Classifier: Programming Language :: Python :: 3.12
Classifier: Topic :: Software Development :: Build Tools
Classifier: Topic :: System :: Software Distribution
Classifier: Topic :: Utilities
Requires-Python: >=3.7
License-File: LICENSE
Requires-Dist: PyYAML>=5.1
Requires-Dist: jinja2>=3.0.0
Provides-Extra: 7z
Requires-Dist: py7zr>=0.20.0; extra == "7z"
Dynamic: license-file
